sphinxcontrib_opendataservices-0.6.0-py3.9-nspkg.pth
sphinxcontrib/opendataservices.py
sphinxcontrib_opendataservices-0.6.0.dist-info/LICENSE
sphinxcontrib_opendataservices-0.6.0.dist-info/METADATA
sphinxcontrib_opendataservices-0.6.0.dist-info/WHEEL
sphinxcontrib_opendataservices-0.6.0.dist-info/namespace_packages.txt
sphinxcontrib_opendataservices-0.6.0.dist-info/top_level.txt
sphinxcontrib_opendataservices-0.6.0.dist-info/RECORD
