Metadata-Version: 2.2
Name: sphinxcontrib-opendataservices
Version: 0.6.0
Home-page: https://github.com/OpenDataServices/sphinxcontrib-opendataservices
Author: Open Data Services
Author-email: code@opendataservices.coop
Classifier: License :: OSI Approved :: MIT License
Requires-Python: >=3.9.0
License-File: LICENSE
Requires-Dist: docutils
Requires-Dist: jsonpointer
Requires-Dist: myst-parser>=0.18.0
Requires-Dist: sphinx
Requires-Dist: sphinxcontrib-opendataservices-jsonschema>=0.5.0
Provides-Extra: test
Requires-Dist: coveralls; extra == "test"
Requires-Dist: flake8; extra == "test"
Requires-Dist: isort; extra == "test"
Requires-Dist: lxml; extra == "test"
Requires-Dist: pytest; extra == "test"
Requires-Dist: pytest-cov; extra == "test"
Provides-Extra: docs
Requires-Dist: sphinx; extra == "docs"
Requires-Dist: odsc-default-sphinx-theme; extra == "docs"
Dynamic: author
Dynamic: author-email
Dynamic: classifier
Dynamic: home-page
Dynamic: provides-extra
Dynamic: requires-dist
Dynamic: requires-python
